<?xml version="1.0" encoding="UTF-8"?>
<domotic xmlns="http://dlvmechanografie.eu/DomoticConfig" xmlns:xsi="http://www.w3.org/2001/XMLSchema-instance"
	xsi:schemaLocation="http://dlvmechanografie.eu/DomoticConfig DomoticConfig.xsd ">

	<switch name="SchakLichtInkom" longClick="true" />
	<lamp name="LichtInkom" />
	<switch name="SchakLichtWC0" desc="Licht WC gelijkvloers." />
	<lamp name="LichtWC0" />
	<switch name="SchakVentilatorWC0" />
	<fan name="VentilatorWC0" lamp="LichtWC0" />
	<switch name="SchakLichtGaragePoort" />
	<lamp name="LichtGaragePoort" />
	<switch name="SchakLichtGarageTuin" />
	<lamp name="LichtGarageTuin" />
	<switch name="SchakLichtKeuken" />
	<lamp name="LichtKeuken" />
	<switch name="SchakLichtBadk0" />
	<lamp name="LichtBadk0" />
	<switch name="SchakVentilatorBadk0" />
	<fan name="VentilatorBadk0" />
	<dimmerSwitches name="SchakLichtVeranda" />
	<dimmedLamp name="LichtVeranda" fullOnHwOutput="4095" />
	<dimmerSwitches name="SchakLichtCircanteRondom" />
	<dimmedLamp name="LichtCircanteRondom" fullOnHwOutput="4095" />
	<switch name="SchakLichtCircante" />
	<lamp name="LichtCircante" />
	<dimmerSwitches name="SchakLichtZithoek" />
	<dimmedLamp name="LichtZithoek" fullOnHwOutput="4095" />
	<switch name="SchakLichtBureau" />
	<lamp name="LichtBureau" />
	<switchboard name="LampenBeneden">
		<connection switch="SchakLichtInkom" lamp="LichtInkom" allOff="true" />
		<connection switch="SchakLichtWC0" lamp="LichtWC0" />
		<connection switch="SchakLichtGaragePoort" lamp="LichtGaragePoort" />
		<connection switch="SchakLichtGarageTuin" lamp="LichtGarageTuin" />
		<connection switch="SchakLichtKeuken" lamp="LichtKeuken" />
		<connection switch="SchakLichtBadk0" lamp="LichtBadk0" />
		<connection switch="SchakLichtCircante" lamp="LichtCircante" />
		<connection switch="SchakLichtBureau" lamp="LichtBureau" />
	</switchboard>
	<switchboardFans name="Ventilatie">
		<connection switch="SchakVentilatorWC0" fan="VentilatorWC0" />
		<connection switch="SchakVentilatorBadk0" fan="VentilatorBadk0" />
	</switchboardFans>
	<switchboardDimmer name="Dimmers">
		<connection dimmedLamp="LichtVeranda" dimmerSwitch="SchakLichtVeranda" />
		<connection dimmedLamp="LichtCircanteRondom" dimmerSwitch="SchakLichtCircanteRondom" />
		<connection dimmedLamp="LichtZithoek" dimmerSwitch="SchakLichtZithoek" />
		<allSwitch switch="SchakLichtInkom" allOff="true" />
	</switchboardDimmer>

	<switch name="SchakLichtGangBoven" />
	<lamp name="LichtGangBoven" />
	<switch name="SchakLichtBadk1" />
	<lamp name="LichtBadk1" />
	<switch name="SchakLichtTomasWand" />
	<lamp name="LichtTomasWand" />
	<switch name="SchakLichtTomasSpots" /><!-- TODO nakijken of klopt met bedrading -->
	<lamp name="LichtTomasSpots" /><!-- TODO nakijken of klopt met relais -->
	<switch name="SchakLichtDriesWand" />
	<lamp name="LichtDriesWand" />
	<switch name="SchakLichtDries" />
	<lamp name="LichtDries" />
	<switch name="SchakLichtRoosWand" />
	<lamp name="LichtRoosWand" />
	<switch name="SchakLichtRoos" />
	<lamp name="LichtRoos" />
	<switchboard name="LampenBoven">
		<connection switch="SchakLichtGangBoven" lamp="LichtGangBoven" />
		<connection switch="SchakLichtBadk1" lamp="LichtBadk1" />
		<connection switch="SchakLichtTomasWand" lamp="LichtTomasWand" />
		<connection switch="SchakLichtTomasSpots" lamp="LichtTomasSpots" />
		<connection switch="SchakLichtDriesWand" lamp="LichtDriesWand" />
		<connection switch="SchakLichtDries" lamp="LichtDries" />
		<connection switch="SchakLichtRoosWand" lamp="LichtRoosWand" />
		<connection switch="SchakLichtRoos" lamp="LichtRoos" />
		<allSwitch switch="SchakLichtInkom" allOff="true" />
	</switchboard>

	<timerDayNight name="TimerNacht">
		<on hour="20" minute="30" />
		<off hour="6" minute="0" />
	</timerDayNight>
	<lamp name="LichtNacht" />
	<switch name="SchakBuitenTuin" />
	<lamp name="LichtTerras" />
	<switchboard name="Buiten1">
		<connection switch="SchakBuitenTuin" lamp="LichtTerras" />
		<c-timer timer="TimerNacht" lamp="LichtNacht" />
	</switchboard>
	
	<!-- TODO Hieronder correct doen. Hack, om te zorgen dat 1 schakelaar twee relais aanstuurt. -->
	<lamp name="StopkBuiten" />
	<switchboard name="Buiten2">
		<connection switch="SchakBuitenTuin" lamp="StopkBuiten" />
	</switchboard>

	<screen name="ScreenTomas" />
	<screen name="ScreenDriesTuin" />
	<screen name="ScreenDriesOpzij" />
	<screen name="ScreenRoos" />
	<screen name="ScreenBreed" />
	<screen name="ScreenLang" />
	<screen name="ScreenKeuken" />
	<switch name="SchakScreenTomasUp" />
	<switch name="SchakScreenTomasDown" />
	<switch name="SchakScreenDriesTuinUp" />
	<switch name="SchakScreenDriesTuinDown" />
	<switch name="SchakScreenDriesOpzijUp" />
	<switch name="SchakScreenDriesOpzijDown" />
	<switch name="SchakScreenRoosUp" />
	<switch name="SchakScreenRoosDown" />
	<switch name="SchakScreenBreedUp" />
	<switch name="SchakScreenBreedDown" />
	<switch name="SchakScreenLangUp" />
	<switch name="SchakScreenLangDown" />
	<switch name="SchakScreenKeukenUp" />
	<switch name="SchakScreenKeukenDown" />
	<switch name="SchakScreenAllUp" />
	<switch name="SchakScreenAllDown" />
	<switchboardScreens name="Screens">
		<connection screen="ScreenTomas" switchUp="SchakScreenTomasUp"
			switchDown="SchakScreenTomasDown" />
		<connection screen="ScreenDriesTuin" switchUp="SchakScreenDriesTuinUp"
			switchDown="SchakScreenDriesTuinDown" />
		<connection screen="ScreenDriesOpzij" switchUp="SchakScreenDriesOpzijUp"
			switchDown="SchakScreenDriesOpzijDown" />
		<connection screen="ScreenRoos" switchUp="SchakScreenRoosUp"
			switchDown="SchakScreenRoosDown" />
		<connection screen="ScreenBreed" switchUp="SchakScreenBreedUp"
			switchDown="SchakScreenBreedDown" />
		<connection screen="ScreenLang" switchUp="SchakScreenLangUp"
			switchDown="SchakScreenLangDown" />
		<connection screen="ScreenKeuken" switchUp="SchakScreenKeukenUp"
			switchDown="SchakScreenKeukenDown" />
		<allUpDownSwitches allDownSwitch="SchakScreenAllDown"
			allUpSwitch="SchakScreenAllUp" />
	</switchboardScreens>
</domotic>
